PKG-INFO
setup.py
ricebox/__init__.py
ricebox/bot.py
ricebox/special.py
ricebox.egg-info/PKG-INFO
ricebox.egg-info/SOURCES.txt
ricebox.egg-info/dependency_links.txt
ricebox.egg-info/entry_points.txt
ricebox.egg-info/not-zip-safe
ricebox.egg-info/requires.txt
ricebox.egg-info/top_level.txt