Metadata-Version: 1.0
Name: ricebox
Version: 0.1.4
Summary: Grabs the daily special from the rice box in bristol.
Home-page: http://freespace.virgin.net/kuanwai.law/page3.html
Author: Alan Hoey
Author-email: alan.hoey@teamrubber.com
License: GPL
Keywords: rice box chinese
Platform: UNKNOWN
Classifier: Environment :: Console
Classifier: Intended Audience :: Other Audience
Classifier: Natural Language :: English
Classifier: Topic :: Other/Nonlisted Topic
